arrivaltimes.py
driftlaw.py
driftrate.py
frbgui.py
frbgui-0.11.0.data/scripts/frbgui
frbgui-0.11.0.dist-info/LICENCE.md
frbgui-0.11.0.dist-info/METADATA
frbgui-0.11.0.dist-info/WHEEL
frbgui-0.11.0.dist-info/entry_points.txt
frbgui-0.11.0.dist-info/top_level.txt
frbgui-0.11.0.dist-info/RECORD
