Metadata-Version: 2.1
Name: frbgui
Version: 0.11.0
Summary: GUI and utilities for processing Fast Radio Burst waterfalls
Home-page: https://github.com/mef51/frbgui
Author: Mohammed Chamma
Author-email: mchamma@uwo.ca
License: MIT
Classifier: Programming Language :: Python :: 3
Classifier: License :: OSI Approved :: MIT License
Classifier: Operating System :: OS Independent
Classifier: Development Status :: 3 - Alpha
Classifier: Intended Audience :: Science/Research
Classifier: Topic :: Scientific/Engineering :: Astronomy
Requires-Python: >=3.6
License-File: LICENCE.md
Requires-Dist: matplotlib>=3.7.2
Requires-Dist: numpy>=1.24.4
Requires-Dist: dearpygui>=1.9.1
Requires-Dist: dearpygui_ext>=0.9.5
Requires-Dist: your>=0.6.7
Requires-Dist: pandas>=2.1.0
Requires-Dist: tqdm>=4.65.0
